[{
        "id": 1,
        "target": "kaykay",
        "forbidden": [
            "binmek",
            "çocuk",
            "tekerlek",
            "tahta",
            "paten"
        ]
    },
    {
        "id": 2,
        "target": "şölen",
        "forbidden": [
            "kutlama",
            "yemek",
            "içmek",
            "ziyafet",
            "eğlence"
        ]
    },
    {
        "id": 3,
        "target": "köse",
        "forbidden": [
            "kıl",
            "bıyık",
            "sakal",
            "tüy",
            "tıraş"
        ]
    },
    {
        "id": 4,
        "target": "yıl dönümü",
        "forbidden": [
            "kutlama",
            "evlilik",
            "ölüm",
            "gün",
            "kuruluş"
        ]
    },
    {
        "id": 5,
        "target": "süvari",
        "forbidden": [
            "at",
            "asker",
            "binmek",
            "savaş",
            "piyade"
        ]
    },
    {
        "id": 6,
        "target": "espri yapmak",
        "forbidden": [
            "komik",
            "şaka",
            "anlatmak",
            "gülmek",
            "kahkaha"
        ]
    },
    {
        "id": 7,
        "target": "şaman",
        "forbidden": [
            "din",
            "eski",
            "büyü",
            "ruh",
            "iyileştirmek"
        ]
    },
    {
        "id": 8,
        "target": "goran bregoviç",
        "forbidden": [
            "Çingeneler Zamanı",
            "Yugoslavya",
            "müzisyen",
            "Emir Kusturica",
            "Mustafa"
        ]
    },
    {
        "id": 9,
        "target": "satır",
        "forbidden": [
            "bıçak",
            "et",
            "kesmek",
            "baş",
            "doğramak"
        ]
    },
    {
        "id": 10,
        "target": "can simidi",
        "forbidden": [
            "deniz",
            "yuvarlak",
            "vapur",
            "boğulmak",
            "gemi"
        ]
    },
    {
        "id": 11,
        "target": "sümen",
        "forbidden": [
            "ofis",
            "masa",
            "yazmak",
            "saklamak",
            "deri"
        ]
    },
    {
        "id": 12,
        "target": "kangal",
        "forbidden": [
            "hayvan",
            "köpek",
            "Sivas",
            "sucuk",
            "kurt"
        ]
    },
    {
        "id": 13,
        "target": "kaldıraç",
        "forbidden": [
            "yük",
            "ağır",
            "kuvvet",
            "çubuk",
            "fizik"
        ]
    },
    {
        "id": 14,
        "target": "aztekler",
        "forbidden": [
            "Meksika",
            "uygarlık",
            "eski",
            "İmparatorluk",
            "İnkalar"
        ]
    },
    {
        "id": 15,
        "target": "pestil",
        "forbidden": [
            "üzüm",
            "dut",
            "kuru",
            "çıkmak",
            "yorgun"
        ]
    },
    {
        "id": 16,
        "target": "dandik",
        "forbidden": [
            "kötü",
            "sahte",
            "kalitesiz",
            "uyduruk",
            "taklit"
        ]
    },
    {
        "id": 17,
        "target": "psikoloji",
        "forbidden": [
            "sosyoloji",
            "psikiyatri",
            "ruhbilim",
            "depresyon",
            "Freud"
        ]
    },
    {
        "id": 18,
        "target": "püskürmek",
        "forbidden": [
            "yanardağ",
            "lav",
            "su",
            "çıkarmak",
            "fışkırmak"
        ]
    },
    {
        "id": 19,
        "target": "domino",
        "forbidden": [
            "taş",
            "oyun",
            "devirmek",
            "dikdörtgen",
            "nokta"
        ]
    },
    {
        "id": 20,
        "target": "adam asmaca",
        "forbidden": [
            "oyun",
            "kelime",
            "bulmak",
            "çizmek",
            "harf"
        ]
    },
    {
        "id": 21,
        "target": "şakşuka",
        "forbidden": [
            "yemek",
            "patlıcan",
            "Tarık Mengüç",
            "meze",
            "şarkı"
        ]
    },
    {
        "id": 22,
        "target": "hörgüç",
        "forbidden": [
            "deve",
            "kambur",
            "sırt",
            "çöl",
            "hayvan"
        ]
    },
    {
        "id": 23,
        "target": "kuru sıkı",
        "forbidden": [
            "tabanca",
            "silah",
            "ateş etmek",
            "patlatmak",
            "gerçek"
        ]
    },
    {
        "id": 24,
        "target": "ömür",
        "forbidden": [
            "yaşam",
            "hayat",
            "ölüm",
            "geçmek",
            "yaşlanmak"
        ]
    },
    {
        "id": 25,
        "target": "magma",
        "forbidden": [
            "yer altı",
            "volkan",
            "erimek",
            "yanardağ",
            "lav"
        ]
    },
    {
        "id": 26,
        "target": "çayır",
        "forbidden": [
            "otlamak",
            "inek",
            "yeşil",
            "çimen",
            "piknik"
        ]
    },
    {
        "id": 27,
        "target": "kasko",
        "forbidden": [
            "araba",
            "araç",
            "sigorta",
            "otomobil",
            "kaza"
        ]
    },
    {
        "id": 28,
        "target": "karamel",
        "forbidden": [
            "tatlı",
            "kahve",
            "dondurma",
            "şeker",
            "yakmak"
        ]
    },
    {
        "id": 29,
        "target": "zamane",
        "forbidden": [
            "çocuk",
            "bugün",
            "genç",
            "şimdi",
            "yakınmak"
        ]
    },
    {
        "id": 30,
        "target": "maksat",
        "forbidden": [
            "amaç",
            "aşmak",
            "istemek",
            "neden",
            "sebep"
        ]
    },
    {
        "id": 31,
        "target": "kese kağıdı",
        "forbidden": [
            "meyve",
            "torba",
            "taşımak",
            "poşet",
            "kestane"
        ]
    },
    {
        "id": 32,
        "target": "gıcırtı",
        "forbidden": [
            "ses",
            "kapı",
            "yağlamak",
            "tahta",
            "pas"
        ]
    },
    {
        "id": 33,
        "target": "jant",
        "forbidden": [
            "araba",
            "parça",
            "tekerlek",
            "lastik",
            "çelik"
        ]
    },
    {
        "id": 34,
        "target": "sait faik abasıyanık",
        "forbidden": [
            "edebiyat",
            "yazar",
            "hikaye",
            "Türk",
            "kitap"
        ]
    },
    {
        "id": 35,
        "target": "başüstüne",
        "forbidden": [
            "emir vermek",
            "komuta",
            "istemek",
            "yerine getirmek",
            "selam söylemek"
        ]
    },
    {
        "id": 36,
        "target": "şahin",
        "forbidden": [
            "kartal",
            "doğan",
            "kuş",
            "yırtıcı",
            "araba"
        ]
    },
    {
        "id": 37,
        "target": "müjde ar",
        "forbidden": [
            "sinema",
            "oyuncu",
            "seksi",
            "Aysel Gürel",
            "arabesk"
        ]
    },
    {
        "id": 38,
        "target": "uzo",
        "forbidden": [
            "Yunan",
            "rakı",
            "su",
            "içki",
            "alkol"
        ]
    },
    {
        "id": 39,
        "target": "boğmaca",
        "forbidden": [
            "hastalık",
            "çocuk",
            "öksürmek",
            "bulaşıcı",
            "aşı"
        ]
    },
    {
        "id": 40,
        "target": "başüstüne",
        "forbidden": [
            "emir",
            "komuta",
            "istemek",
            "yerine",
            "selam"
        ]
    },
    {
        "id": 41,
        "target": "rengi atmak",
        "forbidden": [
            "korkmak",
            "yıkamak",
            "solmak",
            "yüz",
            "sararmak"
        ]
    },
    {
        "id": 42,
        "target": "canına kastetmek",
        "forbidden": [
            "teşebbüs",
            "öldürmek",
            "yaralamak",
            "cinayet",
            "hazırlanmak"
        ]
    },
    {
        "id": 43,
        "target": "dazlak",
        "forbidden": [
            "kel",
            "saç",
            "dökülmek",
            "asker",
            "kazıtmak"
        ]
    },
    {
        "id": 44,
        "target": "kolaj",
        "forbidden": [
            "resim",
            "birleştirmek",
            "kesmek",
            "yapıştırmak",
            "fotoğraf"
        ]
    },
    {
        "id": 45,
        "target": "testere",
        "forbidden": [
            "film",
            "korku",
            "alet",
            "kesmek",
            "ağaç"
        ]
    },
    {
        "id": 46,
        "target": "şehrazat",
        "forbidden": [
            "1001 Gece",
            "masal",
            "kahraman",
            "anlatmak",
            "Bergüzar Korel"
        ]
    },
    {
        "id": 47,
        "target": "terminatör",
        "forbidden": [
            "Arnold Schwarzenegger",
            "robot",
            "Sarah Connor",
            "sinema",
            "bilim kurgu"
        ]
    },
    {
        "id": 48,
        "target": "galata kulesi",
        "forbidden": [
            "İstanbul",
            "Beyoğlu",
            "Ceneviz",
            "Hezarfen",
            "yüksek"
        ]
    },
    {
        "id": 49,
        "target": "fobi",
        "forbidden": [
            "korku",
            "örümcek",
            "yükseklik",
            "aşırı",
            "panik"
        ]
    },
    {
        "id": 50,
        "target": "çelik kasa",
        "forbidden": [
            "para",
            "değerli",
            "mücevher",
            "ev",
            "saklamak"
        ]
    },
    {
        "id": 51,
        "target": "kazan",
        "forbidden": [
            "kepçe",
            "pişirmek",
            "büyük",
            "tencere",
            "yemek"
        ]
    },
    {
        "id": 52,
        "target": "ispirto",
        "forbidden": [
            "alkol",
            "lamba",
            "kolonya",
            "içmek",
            "mor"
        ]
    },
    {
        "id": 53,
        "target": "fizik tedavi",
        "forbidden": [
            "fıtık",
            "kas",
            "jimnastik",
            "doktor",
            "ortopedi"
        ]
    },
    {
        "id": 54,
        "target": "papirüs",
        "forbidden": [
            "kağıt",
            "Mısır",
            "yazmak",
            "bitki",
            "parşömen"
        ]
    },
    {
        "id": 55,
        "target": "sensör",
        "forbidden": [
            "ötmek",
            "park",
            "araba",
            "alarm",
            "ışık"
        ]
    },
    {
        "id": 56,
        "target": "üstat",
        "forbidden": [
            "usta",
            "bilgi",
            "yetenek",
            "en iyi",
            "sanatçı"
        ]
    },
    {
        "id": 57,
        "target": "neşter",
        "forbidden": [
            "ameliyat",
            "bıçak",
            "kesmek",
            "cerrah",
            "doktor"
        ]
    },
    {
        "id": 58,
        "target": "antikor",
        "forbidden": [
            "hastalık",
            "zarar",
            "madde",
            "vücut",
            "üretmek"
        ]
    },
    {
        "id": 59,
        "target": "kafa tutmak",
        "forbidden": [
            "kavga etmek",
            "tartışmak",
            "karşı gelmek",
            "boyun eğmek",
            "diklenmek"
        ]
    },
    {
        "id": 60,
        "target": "jön türkler",
        "forbidden": [
            "Osmanlı",
            "meşrutiyet",
            "aydın",
            "topluluk",
            "İttihat ve Terakki"
        ]
    },
    {
        "id": 61,
        "target": "abone",
        "forbidden": [
            "dergi",
            "ay",
            "YouTube",
            "Yonca Evcimik",
            "Twitch"
        ]
    },
    {
        "id": 62,
        "target": "soğuk algınlığı",
        "forbidden": [
            "nezle",
            "üşütmek",
            "hasta",
            "burun",
            "boğaz"
        ]
    },
    {
        "id": 63,
        "target": "akademisyen",
        "forbidden": [
            "üniversite",
            "ders",
            "hoca",
            "öğretim üyesi",
            "profesör"
        ]
    },
    {
        "id": 64,
        "target": "hayko cepkin",
        "forbidden": [
            "müzisyen",
            "alternatif",
            "dövme",
            "şarkı",
            "marjinal"
        ]
    },
    {
        "id": 65,
        "target": "rekabet",
        "forbidden": [
            "hırs",
            "çekişme",
            "yarışma",
            "rakip",
            "spor"
        ]
    },
    {
        "id": 66,
        "target": "şehzade",
        "forbidden": [
            "padişah",
            "çocuk",
            "sultan",
            "prens",
            "erkek"
        ]
    },
    {
        "id": 67,
        "target": "tekerleme",
        "forbidden": [
            "bilmece",
            "kafiye",
            "söylemek",
            "mani",
            "masal"
        ]
    },
    {
        "id": 68,
        "target": "konuksever",
        "forbidden": [
            "misafirperver",
            "ağırlamak",
            "ikram",
            "yemek",
            "çağırmak"
        ]
    },
    {
        "id": 69,
        "target": "horozlanmak",
        "forbidden": [
            "dayılanmak",
            "kafa tutmak",
            "diklenmek",
            "kavga",
            "cesaret"
        ]
    },
    {
        "id": 70,
        "target": "izdivaç",
        "forbidden": [
            "evlenmek",
            "yuva",
            "gelin",
            "damat",
            "nikah"
        ]
    },
    {
        "id": 71,
        "target": "louvre",
        "forbidden": [
            "Paris",
            "Fransa",
            "müze",
            "saray",
            "Mona Lisa"
        ]
    },
    {
        "id": 72,
        "target": "midye dolma",
        "forbidden": [
            "pilav",
            "yiyecek",
            "tezgah",
            "sokak",
            "limon"
        ]
    },
    {
        "id": 73,
        "target": "oyun havası",
        "forbidden": [
            "göbek",
            "dans etmek",
            "oryantal",
            "müzik",
            "eğlenmek"
        ]
    },
    {
        "id": 74,
        "target": "solak",
        "forbidden": [
            "sağlak",
            "el",
            "yazmak",
            "tutmak",
            "kullanmak"
        ]
    },
    {
        "id": 75,
        "target": "mikrofon",
        "forbidden": [
            "şarkı",
            "sunucu",
            "tutmak",
            "sahne",
            "ses"
        ]
    },
    {
        "id": 76,
        "target": "bitlenmek",
        "forbidden": [
            "hayvan",
            "küçük",
            "pire",
            "saç",
            "kaşınmak"
        ]
    },
    {
        "id": 77,
        "target": "şişirmek",
        "forbidden": [
            "balon",
            "lastik",
            "üflemek",
            "pompa",
            "hava"
        ]
    },
    {
        "id": 78,
        "target": "ananas",
        "forbidden": [
            "meyve",
            "tropikal",
            "sebze",
            "konserve",
            "yemek"
        ]
    },
    {
        "id": 79,
        "target": "kinaye",
        "forbidden": [
            "iğneleme",
            "dolaylı",
            "ima etmek",
            "üstü kapalı",
            "laf atmak"
        ]
    },
    {
        "id": 80,
        "target": "yalap şap",
        "forbidden": [
            "üstünkörü",
            "gelişigüzel",
            "temizlik",
            "iş",
            "cevaplamak"
        ]
    },
    {
        "id": 81,
        "target": "getto",
        "forbidden": [
            "mahalle",
            "şehir",
            "azınlık",
            "yabancı",
            "yaşamak"
        ]
    },
    {
        "id": 82,
        "target": "lafazan",
        "forbidden": [
            "konuşmak",
            "geveze",
            "söz",
            "hazırcevap",
            "anlatmak"
        ]
    },
    {
        "id": 83,
        "target": "gafil avlamak",
        "forbidden": [
            "hazırlıksız",
            "yakalanmak",
            "beklenmedik",
            "zayıf",
            "enselemek"
        ]
    },
    {
        "id": 84,
        "target": "güneş banyosu",
        "forbidden": [
            "yanmak",
            "krem",
            "yatmak",
            "tatil",
            "yaz"
        ]
    },
    {
        "id": 85,
        "target": "afyon",
        "forbidden": [
            "şehir",
            "sucuk",
            "haşhaş",
            "kaymak",
            "patlamak"
        ]
    },
    {
        "id": 86,
        "target": "babil kulesi",
        "forbidden": [
            "efsane",
            "inşa etmek",
            "Tanrı",
            "ulaşmak",
            "eski"
        ]
    },
    {
        "id": 87,
        "target": "penelope cruz",
        "forbidden": [
            "sinema",
            "oyuncu",
            "İspanyol",
            "Oscar",
            "esmer"
        ]
    },
    {
        "id": 88,
        "target": "gammaz",
        "forbidden": [
            "ispiyonlamak",
            "söylemek",
            "ara bozucu",
            "kötülemek",
            "dedikodu"
        ]
    },
    {
        "id": 89,
        "target": "ayrıntı",
        "forbidden": [
            "detay",
            "teferruat",
            "küçük",
            "şeytan",
            "takılmak"
        ]
    },
    {
        "id": 90,
        "target": "haham",
        "forbidden": [
            "Yahudi",
            "Musevi",
            "imam",
            "rahip",
            "sinagog"
        ]
    },
    {
        "id": 91,
        "target": "safir",
        "forbidden": [
            "taş",
            "mücevher",
            "değerli",
            "yakut",
            "mavi"
        ]
    },
    {
        "id": 92,
        "target": "başköşe",
        "forbidden": [
            "baba",
            "masa",
            "büyük",
            "oturmak",
            "yemek"
        ]
    },
    {
        "id": 93,
        "target": "mekik çekmek",
        "forbidden": [
            "karın kası",
            "egzersiz",
            "göbek",
            "spor",
            "şınav çekmek"
        ]
    },
    {
        "id": 94,
        "target": "florence nightingale",
        "forbidden": [
            "hemşire",
            "hastane",
            "kurmak",
            "ilk",
            "doktor"
        ]
    },
    {
        "id": 95,
        "target": "işkembe",
        "forbidden": [
            "çorba",
            "paça",
            "kokmak",
            "mide",
            "sallamak"
        ]
    },
    {
        "id": 96,
        "target": "çardak",
        "forbidden": [
            "yaz",
            "gölge",
            "bahçe",
            "oturmak",
            "kameriye"
        ]
    },
    {
        "id": 97,
        "target": "eğilim",
        "forbidden": [
            "ilgi",
            "yönelmek",
            "merak",
            "meyilli",
            "istemek"
        ]
    },
    {
        "id": 98,
        "target": "nişasta",
        "forbidden": [
            "şeker",
            "karbonhidrat",
            "yiyecek",
            "patates",
            "mısır"
        ]
    },
    {
        "id": 99,
        "target": "rozet",
        "forbidden": [
            "yaka",
            "sembol",
            "metal",
            "takmak",
            "parti"
        ]
    },
    {
        "id": 100,
        "target": "tepeden bakmak",
        "forbidden": [
            "küçümsemek",
            "görmek",
            "üstün",
            "ukala",
            "mütevazı"
        ]
    },
    {
        "id": 101,
        "target": "hafriyat",
        "forbidden": [
            "inşaat",
            "toprak",
            "bina",
            "kazmak",
            "kamyon"
        ]
    },
    {
        "id": 102,
        "target": "çatalhöyük",
        "forbidden": [
            "arkeoloji",
            "antik",
            "Anadolu",
            "eski",
            "kazı"
        ]
    },
    {
        "id": 103,
        "target": "sendrom",
        "forbidden": [
            "belirti",
            "hastalık",
            "bunalım",
            "pazartesi",
            "sıkıntı"
        ]
    },
    {
        "id": 104,
        "target": "zonklamak",
        "forbidden": [
            "baş ağrısı",
            "vurmak",
            "ağrımak",
            "şakak",
            "beyin"
        ]
    },
    {
        "id": 105,
        "target": "yazlık",
        "forbidden": [
            "ev",
            "oturmak",
            "gitmek",
            "deniz",
            "tatil"
        ]
    },
    {
        "id": 106,
        "target": "hacı bektaş-ı veli",
        "forbidden": [
            "Alevi",
            "tasavvuf",
            "şenlik",
            "Mevlana",
            "fıkra"
        ]
    },
    {
        "id": 107,
        "target": "mahsus",
        "forbidden": [
            "şaka",
            "özgü",
            "bilerek",
            "kasten",
            "isteyerek"
        ]
    },
    {
        "id": 108,
        "target": "çömlek",
        "forbidden": [
            "çanak",
            "toprak",
            "kap",
            "tencere",
            "pişirmek"
        ]
    },
    {
        "id": 109,
        "target": "spa",
        "forbidden": [
            "masaj",
            "sauna",
            "otel",
            "bakım",
            "rahatlamak"
        ]
    },
    {
        "id": 110,
        "target": "tasarım",
        "forbidden": [
            "dizayn",
            "sanat",
            "mobilya",
            "ürün",
            "yaratmak"
        ]
    },
    {
        "id": 111,
        "target": "tornavida",
        "forbidden": [
            "yıldız",
            "alet",
            "tamir",
            "monte etmek",
            "döndürmek"
        ]
    },
    {
        "id": 112,
        "target": "barınak",
        "forbidden": [
            "hayvan",
            "sokak köpeği",
            "yaşamak",
            "kalmak",
            "korunmak"
        ]
    },
    {
        "id": 113,
        "target": "gazi",
        "forbidden": [
            "M. Kemal Atatürk",
            "savaş",
            "yaralanmak",
            "şehit",
            "ölmek"
        ]
    },
    {
        "id": 114,
        "target": "bambi",
        "forbidden": [
            "yavru",
            "geyik",
            "hayvan",
            "ceylan",
            "çizgi film"
        ]
    },
    {
        "id": 115,
        "target": "çantada keklik",
        "forbidden": [
            "kesim",
            "iş",
            "kolay",
            "elde etmek",
            "çocuk oyuncağı"
        ]
    },
    {
        "id": 116,
        "target": "muhit",
        "forbidden": [
            "semt",
            "yaşamak",
            "çevre",
            "mahalle",
            "ev"
        ]
    },
    {
        "id": 117,
        "target": "feng shui",
        "forbidden": [
            "dekorasyon",
            "tarz",
            "Uzak Doğu",
            "mekan",
            "ev"
        ]
    },
    {
        "id": 118,
        "target": "kabza",
        "forbidden": [
            "silah",
            "tabanca",
            "tutmak",
            "sap",
            "kılıç"
        ]
    },
    {
        "id": 119,
        "target": "manda",
        "forbidden": [
            "öküz",
            "inek",
            "dana",
            "hayvan",
            "Amerika"
        ]
    },
    {
        "id": 120,
        "target": "tom sawyer",
        "forbidden": [
            "Mark Twain",
            "roman",
            "macera",
            "Huckleberry Finn",
            "çocuk"
        ]
    },
    {
        "id": 121,
        "target": "hafıza",
        "forbidden": [
            "beyin",
            "hatırlamak",
            "anı",
            "bilgisayar",
            "unutmak"
        ]
    },
    {
        "id": 122,
        "target": "hayal meyal",
        "forbidden": [
            "hatırlamak",
            "belirsiz",
            "düş",
            "açık",
            "net"
        ]
    },
    {
        "id": 123,
        "target": "anırmak",
        "forbidden": [
            "eşek",
            "bağırmak",
            "at",
            "hayvan",
            "kişnemek"
        ]
    },
    {
        "id": 124,
        "target": "dalyan",
        "forbidden": [
            "Akdeniz",
            "kaplumbağa",
            "Antalya",
            "Caretta",
            "köfte"
        ]
    },
    {
        "id": 125,
        "target": "fransız ihtilali",
        "forbidden": [
            "devrim",
            "halk",
            "ayaklanma",
            "kral",
            "tarih"
        ]
    },
    {
        "id": 126,
        "target": "astigmat",
        "forbidden": [
            "göz",
            "hipermetrop",
            "miyop",
            "bozuk",
            "görmek"
        ]
    },
    {
        "id": 127,
        "target": "minyon",
        "forbidden": [
            "ufak",
            "kısa",
            "küçük",
            "boy",
            "tip"
        ]
    },
    {
        "id": 128,
        "target": "hükmetmek",
        "forbidden": [
            "imparator",
            "kral",
            "yönetmek",
            "emir vermek",
            "ülke"
        ]
    },
    {
        "id": 129,
        "target": "kankan",
        "forbidden": [
            "dans",
            "Fransız",
            "Red Kit",
            "bacak",
            "bar"
        ]
    },
    {
        "id": 130,
        "target": "topuz",
        "forbidden": [
            "saç",
            "toplamak",
            "düğün",
            "kuaför",
            "gelin"
        ]
    },
    {
        "id": 131,
        "target": "gönye",
        "forbidden": [
            "iletki",
            "açı",
            "üçgen",
            "ölçmek",
            "cetvel"
        ]
    },
    {
        "id": 132,
        "target": "kerpeten",
        "forbidden": [
            "alet",
            "ağız",
            "çekmek",
            "çivi",
            "sökmek"
        ]
    },
    {
        "id": 133,
        "target": "ebeveyn",
        "forbidden": [
            "anne",
            "baba",
            "çocuk",
            "aile",
            "banyo"
        ]
    },
    {
        "id": 134,
        "target": "stepne",
        "forbidden": [
            "lastik",
            "yedek",
            "tekerlek",
            "patlamak",
            "araba"
        ]
    },
    {
        "id": 135,
        "target": "kısa film",
        "forbidden": [
            "sinema",
            "uzun",
            "festival",
            "dakika",
            "yönetmen"
        ]
    },
    {
        "id": 136,
        "target": "keklik",
        "forbidden": [
            "hayvan",
            "kuş",
            "avlamak",
            "güvercin",
            "vurmak"
        ]
    },
    {
        "id": 137,
        "target": "düz taban",
        "forbidden": [
            "ayak",
            "askerlik",
            "yürümek",
            "ortopedi",
            "topuk"
        ]
    },
    {
        "id": 138,
        "target": "blender",
        "forbidden": [
            "karıştırmak",
            "parçalamak",
            "mutfak",
            "alet",
            "yemek"
        ]
    },
    {
        "id": 139,
        "target": "para üstü",
        "forbidden": [
            "vermek",
            "almak",
            "bozuk",
            "kağıt",
            "hesap"
        ]
    },
    {
        "id": 140,
        "target": "çevreyolu",
        "forbidden": [
            "gitmek",
            "otoban",
            "araba",
            "E-5",
            "TEM"
        ]
    },
    {
        "id": 141,
        "target": "insan kaynakları",
        "forbidden": [
            "meslek",
            "iş",
            "almak",
            "özgeçmiş",
            "mülakat"
        ]
    },
    {
        "id": 142,
        "target": "Ajda Pekkan",
        "forbidden": [
            "şarkıcı",
            "müzik",
            "sarışın",
            "estetik",
            "süper star"
        ]
    },
    {
        "id": 143,
        "target": "kritik",
        "forbidden": [
            "maç",
            "pozisyon",
            "ciddi",
            "önemli",
            "eleştiri"
        ]
    },
    {
        "id": 144,
        "target": "eli ağır",
        "forbidden": [
            "yavaş",
            "yapmak",
            "çabuk",
            "hızlı",
            "iş bitirici"
        ]
    },
    {
        "id": 145,
        "target": "tekzip",
        "forbidden": [
            "yalanlamak",
            "gerçek",
            "gazete",
            "yayınlamak",
            "haber"
        ]
    },
    {
        "id": 146,
        "target": "file",
        "forbidden": [
            "voleybol",
            "pazar",
            "torba",
            "ip",
            "basketbol"
        ]
    },
    {
        "id": 147,
        "target": "çerez",
        "forbidden": [
            "kuruyemiş",
            "bira",
            "cips",
            "fındık",
            "fıstık"
        ]
    },
    {
        "id": 148,
        "target": "zamanaşımı",
        "forbidden": [
            "süre",
            "bitmek",
            "dava",
            "düşmek",
            "yıl"
        ]
    },
    {
        "id": 149,
        "target": "kosinüs",
        "forbidden": [
            "matematik",
            "açı",
            "tanjant",
            "üçgen",
            "trigonometri"
        ]
    },
    {
        "id": 150,
        "target": "yer fıstığı",
        "forbidden": [
            "kuruyemiş",
            "çerez",
            "bira",
            "kabuk",
            "ezme"
        ]
    },
    {
        "id": 151,
        "target": "kontör",
        "forbidden": [
            "yüklemek",
            "telefon",
            "almak",
            "bitmek",
            "kart"
        ]
    },
    {
        "id": 152,
        "target": "halter",
        "forbidden": [
            "spor",
            "kaldırmak",
            "ağırlık",
            "güç",
            "Naim Süleymanoğlu"
        ]
    },
    {
        "id": 153,
        "target": "banko",
        "forbidden": [
            "kesin",
            "at yarışı",
            "kazanmak",
            "bahis",
            "garanti"
        ]
    },
    {
        "id": 154,
        "target": "kış uykusu",
        "forbidden": [
            "ayı",
            "yatmak",
            "soğuk",
            "sürüngen",
            "hayvan"
        ]
    },
    {
        "id": 155,
        "target": "wolverine",
        "forbidden": [
            "kurt adam",
            "pençe",
            "X-Men",
            "mutasyon",
            "Marvel"
        ]
    },
    {
        "id": 156,
        "target": "efor",
        "forbidden": [
            "güç",
            "çaba",
            "harcamak",
            "kalp",
            "test"
        ]
    },
    {
        "id": 157,
        "target": "elişi",
        "forbidden": [
            "dantel",
            "örgü",
            "çeyiz",
            "okul",
            "ders"
        ]
    },
    {
        "id": 158,
        "target": "iş kurmak",
        "forbidden": [
            "dükkan",
            "açmak",
            "patron",
            "kendi",
            "şirket"
        ]
    },
    {
        "id": 159,
        "target": "komisyon",
        "forbidden": [
            "para",
            "almak",
            "emlakçı",
            "kiralamak",
            "satmak"
        ]
    },
    {
        "id": 160,
        "target": "külyutmaz",
        "forbidden": [
            "inanmak",
            "aldanmak",
            "kurnaz",
            "tuzak",
            "hile"
        ]
    },
    {
        "id": 161,
        "target": "bacanak",
        "forbidden": [
            "eş",
            "kardeş",
            "baldız",
            "koca",
            "kız"
        ]
    },
    {
        "id": 162,
        "target": "arsız",
        "forbidden": [
            "şımarık",
            "terbiyesiz",
            "dayak",
            "utanmaz",
            "yüzsüz"
        ]
    },
    {
        "id": 163,
        "target": "pilates",
        "forbidden": [
            "spor",
            "yoga",
            "egzersiz",
            "top",
            "esnetmek"
        ]
    },
    {
        "id": 164,
        "target": "alın teri",
        "forbidden": [
            "emek",
            "çalışmak",
            "dökmek",
            "zahmet",
            "uğraşmak"
        ]
    },
    {
        "id": 165,
        "target": "ponpon",
        "forbidden": [
            "yuvarlak",
            "püskül",
            "kız",
            "süs",
            "maç"
        ]
    },
    {
        "id": 166,
        "target": "aforoz",
        "forbidden": [
            "din",
            "kilise",
            "Hristiyan",
            "çıkarmak",
            "atmak"
        ]
    },
    {
        "id": 167,
        "target": "cem karaca",
        "forbidden": [
            "müzisyen",
            "şapka",
            "ceviz ağacı",
            "Tamirci Çırağı",
            "Barış Manço"
        ]
    },
    {
        "id": 168,
        "target": "prematüre",
        "forbidden": [
            "bebek",
            "erken",
            "doğmak",
            "kuvöz",
            "çocuk"
        ]
    },
    {
        "id": 169,
        "target": "hilal",
        "forbidden": [
            "ay",
            "şekil",
            "dolunay",
            "yıldız",
            "bayrak"
        ]
    },
    {
        "id": 170,
        "target": "çağlayan",
        "forbidden": [
            "şelale",
            "su",
            "akmak",
            "nehir",
            "yüksek"
        ]
    },
    {
        "id": 171,
        "target": "britney spears",
        "forbidden": [
            "şarkıcı",
            "Amerika",
            "sarışın",
            "müzik",
            "dans"
        ]
    },
    {
        "id": 172,
        "target": "bünye",
        "forbidden": [
            "sağlam",
            "hasta",
            "vücut",
            "bağışıklık",
            "yapı"
        ]
    },
    {
        "id": 173,
        "target": "ispanyol paça",
        "forbidden": [
            "kot",
            "pantolon",
            "uç",
            "moda",
            "geniş"
        ]
    },
    {
        "id": 174,
        "target": "çiğ börek",
        "forbidden": [
            "yiyecek",
            "hamur",
            "mantı",
            "kızartmak",
            "Eskişehir"
        ]
    },
    {
        "id": 175,
        "target": "dönme dolap",
        "forbidden": [
            "lunapark",
            "yüksek",
            "çocuk",
            "eğlence",
            "oturmak"
        ]
    },
    {
        "id": 176,
        "target": "günah",
        "forbidden": [
            "suç",
            "işlemek",
            "din",
            "çıkarmak",
            "sevap"
        ]
    },
    {
        "id": 177,
        "target": "sivil toplum",
        "forbidden": [
            "örgüt",
            "devlet",
            "bağımsız",
            "dernek",
            "vakıf"
        ]
    },
    {
        "id": 178,
        "target": "gong",
        "forbidden": [
            "ses",
            "zil",
            "tokmak",
            "çınlamak",
            "vurmak"
        ]
    },
    {
        "id": 179,
        "target": "mayışmak",
        "forbidden": [
            "gevşemek",
            "rahatlamak",
            "sıcak",
            "yemek",
            "rehavet"
        ]
    },
    {
        "id": 180,
        "target": "andromeda",
        "forbidden": [
            "uzay",
            "evren",
            "galaksi",
            "samanyolu",
            "disko"
        ]
    },
    {
        "id": 181,
        "target": "rokfor",
        "forbidden": [
            "peynir",
            "küf",
            "süt",
            "Fransız",
            "beyaz"
        ]
    },
    {
        "id": 182,
        "target": "imambayıldı",
        "forbidden": [
            "patlıcan",
            "yemek",
            "zeytinyağlı",
            "karnıyarık",
            "domates"
        ]
    },
    {
        "id": 183,
        "target": "ogs",
        "forbidden": [
            "köprü",
            "HGS",
            "para",
            "gişe",
            "geçmek"
        ]
    },
    {
        "id": 184,
        "target": "rokoko",
        "forbidden": [
            "mimari",
            "barok",
            "üslup",
            "tatlı",
            "pasta"
        ]
    },
    {
        "id": 185,
        "target": "fethiye",
        "forbidden": [
            "Muğla",
            "Ölüdeniz",
            "tatil",
            "Akdeniz",
            "Kelebekler Vadisi"
        ]
    },
    {
        "id": 186,
        "target": "lebiderya",
        "forbidden": [
            "deniz kenarı",
            "sahil",
            "ev",
            "yazlık",
            "manzara"
        ]
    },
    {
        "id": 187,
        "target": "egzama",
        "forbidden": [
            "alerji",
            "deri",
            "hastalık",
            "kaşınmak",
            "stres"
        ]
    },
    {
        "id": 188,
        "target": "yüzü kızarmak",
        "forbidden": [
            "utanmak",
            "ayıp",
            "sıcak",
            "terlemek",
            "suç"
        ]
    },
    {
        "id": 189,
        "target": "alaska",
        "forbidden": [
            "frigo",
            "Amerika",
            "soğuk",
            "eyalet",
            "Rusya"
        ]
    },
    {
        "id": 190,
        "target": "ton balığı",
        "forbidden": [
            "konserve",
            "sandviç",
            "salata",
            "yemek",
            "orkinos"
        ]
    },
    {
        "id": 191,
        "target": "kıtlama",
        "forbidden": [
            "çay",
            "içmek",
            "şeker",
            "ısırmak",
            "Erzurum"
        ]
    },
    {
        "id": 192,
        "target": "sığınak",
        "forbidden": [
            "savaş",
            "bomba",
            "kaçmak",
            "yer altı",
            "nükleer"
        ]
    },
    {
        "id": 193,
        "target": "sandık",
        "forbidden": [
            "çeyiz",
            "tahta",
            "eşya",
            "seçim",
            "oy atmak"
        ]
    },
    {
        "id": 194,
        "target": "dinar",
        "forbidden": [
            "para",
            "birim",
            "Arap",
            "Sırp",
            "altın"
        ]
    },
    {
        "id": 195,
        "target": "kameraman",
        "forbidden": [
            "film",
            "televizyon",
            "çekmek",
            "omuz",
            "taşımak"
        ]
    },
    {
        "id": 196,
        "target": "göçebe",
        "forbidden": [
            "at",
            "yerleşik",
            "çingene",
            "Yörük",
            "çadır"
        ]
    },
    {
        "id": 197,
        "target": "bahane",
        "forbidden": [
            "aramak",
            "uydurmak",
            "yalan",
            "sebep",
            "söylemek"
        ]
    },
    {
        "id": 198,
        "target": "çapak",
        "forbidden": [
            "göz",
            "sabah",
            "kurumak",
            "uyku",
            "kenar"
        ]
    },
    {
        "id": 199,
        "target": "rastlantı",
        "forbidden": [
            "karşılaşmak",
            "tesadüf",
            "beklenmedik",
            "denk gelmek",
            "şans"
        ]
    },
    {
        "id": 200,
        "target": "böbrek",
        "forbidden": [
            "organ",
            "vücut",
            "diyaliz",
            "taş",
            "idrar"
        ]
    }
]